constload/__init__.py
constload/constant_loader.py
constload/exceptions.py
constload/loaders.py
constload-1.0.1.dist-info/LICENCE
constload-1.0.1.dist-info/METADATA
constload-1.0.1.dist-info/WHEEL
constload-1.0.1.dist-info/top_level.txt
constload-1.0.1.dist-info/RECORD
