Metadata-Version: 2.1
Name: constload
Version: 1.0.1
Summary: A package to streamline constant loading and initialisation
Home-page: https://www.github.com/codemicro/constload
Author: Thomas Pain
Author-email: tom@tdpain.net
License: UNKNOWN
Platform: UNKNOWN
Classifier: Programming Language :: Python :: 3
Classifier: Programming Language :: Python :: 3.5
Classifier: Programming Language :: Python :: 3.6
Classifier: Programming Language :: Python :: 3.7
Classifier: Programming Language :: Python :: 3.8
Classifier: License :: OSI Approved :: Mozilla Public License 2.0 (MPL 2.0)
Classifier: Operating System :: OS Independent
Requires-Python: >=3.5
Provides-Extra: yaml
Requires-Dist: PyYAML ; extra == 'yaml'
